ReadDocs/ReadDocs.py
ReadDocs/__init__.py
ReadDocs-1.0.0.dist-info/METADATA
ReadDocs-1.0.0.dist-info/WHEEL
ReadDocs-1.0.0.dist-info/top_level.txt
ReadDocs-1.0.0.dist-info/RECORD
