Metadata-Version: 2.1
Name: ReadDocs
Version: 1.0.0
Summary: A Python package for extracting text from PDF files.
Author: Jayesh vani
Author-email: jayeshvani2@gmail.com
Classifier: Programming Language :: Python :: 3
Classifier: License :: OSI Approved :: MIT License
Classifier: Operating System :: OS Independent
Requires-Dist: PyMuPDF
